NordicUARTSerialDriver/NordicUARTSerialDriver.py
NordicUARTSerialDriver/__init__.py
NordicUARTSerialDriver/example.py
NordicUARTSerialDriver-0.1.1.dist-info/LICENSE
NordicUARTSerialDriver-0.1.1.dist-info/METADATA
NordicUARTSerialDriver-0.1.1.dist-info/WHEEL
NordicUARTSerialDriver-0.1.1.dist-info/top_level.txt
NordicUARTSerialDriver-0.1.1.dist-info/RECORD
