Metadata-Version: 2.1
Name: NordicUARTSerialDriver
Version: 0.1.1
Summary: A virtual serial interface for communications over NordicUART
Author: Lidor Shimoni
Author-email: lidor.shim@gmail.com
Classifier: Programming Language :: Python :: 3
Classifier: License :: OSI Approved :: MIT License
Classifier: Operating System :: OS Independent
Requires-Python: >=3.6
License-File: LICENSE
